teamlead/pw/ecoflow/__init__.py
teamlead/pw/ecoflow/api.py
teamlead/pw/ecoflow/mqtt.py
teamlead_pw_ecoflow-0.2.5.dist-info/METADATA
teamlead_pw_ecoflow-0.2.5.dist-info/WHEEL
teamlead_pw_ecoflow-0.2.5.dist-info/licenses/LICENSE
teamlead_pw_ecoflow-0.2.5.dist-info/RECORD
