Metadata-Version: 2.4
Name: teamlead.pw.ecoflow
Version: 0.2.5
Summary: Ecoflow API Library
Project-URL: Homepage, https://github.com/antongorodezkiy/ecoflow-api
Project-URL: Documentation, https://github.com/antongorodezkiy/ecoflow-api
Project-URL: Repository, https://github.com/antongorodezkiy/ecoflow-api.git
Project-URL: Bug Tracker, https://github.com/antongorodezkiy/ecoflow-api/issues
Project-URL: Changelog, https://github.com/antongorodezkiy/ecoflow-api/blob/master/CHANGELOG.md
Author-email: Eduard Kozachok <admin@teamlead.pw>
Maintainer-email: Eduard Kozachok <admin@teamlead.pw>
License: MIT License
License-File: LICENSE
Keywords: api,ecoflow
Classifier: Development Status :: 4 - Beta
Classifier: Environment :: Console
Classifier: Intended Audience :: Developers
Classifier: License :: OSI Approved :: MIT License
Classifier: Natural Language :: English
Classifier: Operating System :: MacOS :: MacOS X
Classifier: Operating System :: Microsoft :: Windows
Classifier: Operating System :: POSIX
Classifier: Programming Language :: Python
Classifier: Programming Language :: Python :: 3.10
Classifier: Programming Language :: Python :: 3.11
Classifier: Topic :: Home Automation
Classifier: Topic :: Internet
Classifier: Topic :: Software Development :: Libraries
Requires-Python: >=3.10
Requires-Dist: paho-mqtt>=2.1.0
Requires-Dist: requests
